openvto/__init__.py
openvto/client.py
openvto/errors.py
openvto/types.py
openvto/assets/avatars/1.png
openvto/assets/avatars/2.png
openvto/assets/avatars/3.png
openvto/assets/avatars/4.png
openvto/assets/clothes/jackets/1_back.jpg
openvto/assets/clothes/jackets/1_front.jpg
openvto/assets/clothes/jackets/2_back.jpg
openvto/assets/clothes/jackets/2_front.jpg
openvto/assets/clothes/jackets/3_back.jpg
openvto/assets/clothes/jackets/3_front.jpg
openvto/assets/clothes/jackets/4_back.jpg
openvto/assets/clothes/jackets/4_front.jpg
openvto/assets/clothes/pants/1_back.jpg
openvto/assets/clothes/pants/1_front.jpg
openvto/assets/clothes/pants/2_back.jpg
openvto/assets/clothes/pants/2_front.jpg
openvto/assets/clothes/pants/3_back.jpg
openvto/assets/clothes/pants/3_front.jpg
openvto/assets/clothes/pants/4_back.jpg
openvto/assets/clothes/pants/4_front.jpg
openvto/assets/clothes/shirts/1_back.jpg
openvto/assets/clothes/shirts/1_front.jpg
openvto/assets/clothes/shirts/2_back.jpg
openvto/assets/clothes/shirts/2_front.jpg
openvto/assets/clothes/shirts/3_back.jpg
openvto/assets/clothes/shirts/3_front.jpg
openvto/assets/clothes/shirts/4_back.jpg
openvto/assets/clothes/shirts/4_front.jpg
openvto/assets/people/1_posture.jpg
openvto/assets/people/1_selfie.jpg
openvto/assets/people/2_posture.jpg
openvto/assets/people/2_selfie.jpg
openvto/assets/people/3_posture.jpg
openvto/assets/people/3_selfie.jpg
openvto/assets/people/4_posture.jpg
openvto/assets/people/4_selfie.jpg
openvto/example/__init__.py
openvto/pipelines/__init__.py
openvto/pipelines/avatar.py
openvto/pipelines/composer.py
openvto/pipelines/tryon.py
openvto/pipelines/videoloop.py
openvto/prompts/__init__.py
openvto/prompts/avatar.json
openvto/prompts/loader.py
openvto/prompts/tryon.json
openvto/prompts/videoloop.json
openvto/providers/__init__.py
openvto/providers/base.py
openvto/providers/google.py
openvto/providers/mock.py
openvto/utils/__init__.py
openvto/utils/hashing.py
openvto/utils/images.py
openvto/utils/timing.py
openvto-0.1.7.dist-info/METADATA
openvto-0.1.7.dist-info/WHEEL
openvto-0.1.7.dist-info/RECORD
